discotoolkit/CELLiD.py
discotoolkit/CellMapper.py
discotoolkit/DiscoClass.py
discotoolkit/DownloadDiscoData.py
discotoolkit/GeneSearch.py
discotoolkit/GetMetadata.py
discotoolkit/GlobalVariable.py
discotoolkit/Utilities.py
discotoolkit/__init__.py
discotoolkit-1.1.4.dist-info/METADATA
discotoolkit-1.1.4.dist-info/WHEEL
discotoolkit-1.1.4.dist-info/top_level.txt
discotoolkit-1.1.4.dist-info/RECORD
